xarray_selafin_backend/Serafin.py
xarray_selafin_backend/__init__.py
xarray_selafin_backend/xarray_backend.py
xarray_selafin_backend/data/Serafin_var2D.csv
xarray_selafin_backend/data/Serafin_var3D.csv
xarray_selafin_backend/variable/__init__.py
xarray_selafin_backend/variable/variables_2d.py
xarray_selafin_backend/variable/variables_3d.py
xarray_selafin_backend/variable/variables_utils.py
xarray_selafin_backend-0.1.1.dist-info/METADATA
xarray_selafin_backend-0.1.1.dist-info/WHEEL
xarray_selafin_backend-0.1.1.dist-info/entry_points.txt
xarray_selafin_backend-0.1.1.dist-info/top_level.txt
xarray_selafin_backend-0.1.1.dist-info/RECORD
