Metadata-Version: 2.1
Name: xarray-selafin-backend
Version: 0.1.1
Summary: https://github.com/seareport/xarray-selafin
Author: tomsail, lucduron
Author-email: saillour.thomas@gmail.com,  l.duron@cnr.tm.fr
Requires-Python: >=3.9
Requires-Dist: numpy
Requires-Dist: pytest
Requires-Dist: scipy
Requires-Dist: shapely
Requires-Dist: xarray
Requires-Dist: netcdf4
Provides-Extra: dask
Requires-Dist: dask ; extra == 'dask'
Provides-Extra: dev
Requires-Dist: matplotlib ; extra == 'dev'
